split_mac_test/__init__.py
split_mac_test/__main__.py
split_mac_test/window_actions.py
split_screen_mac_test-1.4.0.dist-info/METADATA
split_screen_mac_test-1.4.0.dist-info/WHEEL
split_screen_mac_test-1.4.0.dist-info/entry_points.txt
split_screen_mac_test-1.4.0.dist-info/licenses/LICENSE
split_screen_mac_test-1.4.0.dist-info/RECORD
