Metadata-Version: 2.4
Name: split-screen-mac-test
Version: 1.4.0
Summary: MCP Server for macOS Split Screen Window Management via Native APIs
Author: Beta
License: MIT License
License-File: LICENSE
Keywords: appkit,macos,mcp,pyobjc,quartz,split-screen,tiling,window-management
Requires-Python: >=3.9
Requires-Dist: mcp>=0.1.0
Requires-Dist: pyobjc-framework-cocoa>=9.0
